{
	"format_version": "1.12.0",
	"minecraft:geometry": [
		{
			"description": {
				"identifier": "geometry.unknown",
				"texture_width": 128,
				"texture_height": 128,
				"visible_bounds_width": 8,
				"visible_bounds_height": 3.5,
				"visible_bounds_offset": [0, 1.25, 0]
			},
			"bones": [
				{
					"name": "tornadustherian",
					"pivot": [0, 0, 0]
				},
				{
					"name": "body",
					"parent": "tornadustherian",
					"pivot": [0, 14.39611, -1.6781]
				},
				{
					"name": "right_wing",
					"parent": "body",
					"pivot": [-22.04731, 24.1502, -4.58661]
				},
				{
					"name": "lowerbody",
					"parent": "tornadustherian",
					"pivot": [0, 15.43809, -2.28474],
					"cubes": [
						{"origin": [-3.5, 6.1149, -0.64784], "size": [7, 4, 6], "pivot": [4.5, 10.3149, 0.95216], "rotation": [62.5, 0, 0], "uv": [43, 4]},
						{"origin": [0, 5.4, -12], "size": [0, 7, 6], "pivot": [-1, 17.9, -3.6], "rotation": [32.5, 0, 0], "uv": [101, 43]},
						{"origin": [-4.5, 8.4, -9], "size": [9, 9, 10], "pivot": [3.5, 17.9, -3.6], "rotation": [32.5, 0, 0], "uv": [0, 20]}
					]
				},
				{
					"name": "left_leg",
					"parent": "lowerbody",
					"pivot": [4.4, 9.42427, 1.02053],
					"cubes": [
						{"origin": [2.40831, 5.8, -8.96571], "size": [5, 6, 6], "pivot": [1.40831, 17.9, -3.96571], "rotation": [32.5, -12.5, 0], "uv": [87, 4]}
					]
				},
				{
					"name": "left_leg2",
					"parent": "left_leg",
					"pivot": [4.4, 7.42427, 2.02053],
					"cubes": [
						{"origin": [2.4, 1.82427, 0.02053], "size": [3, 7, 3], "pivot": [4.4, 6.42427, 1.02053], "rotation": [-15, -12.5, 0], "uv": [19, 40]}
					]
				},
				{
					"name": "left_foot",
					"parent": "left_leg2",
					"pivot": [4.4, 3.02427, 1.02053],
					"cubes": [
						{"origin": [2, 0.02427, -2.97947], "size": [4, 3, 6], "pivot": [4.4, 6.42427, 1.02053], "rotation": [0, -12.5, 0], "uv": [39, 26]}
					]
				},
				{
					"name": "left_toe",
					"parent": "left_foot",
					"pivot": [4.85, 1.27427, 2.27053],
					"cubes": [
						{"origin": [3.8, 0.02427, 2.02053], "size": [2, 2, 2], "uv": [75, 51]},
						{"origin": [4.9, 0.02427, 4.02053], "size": [0, 2, 3], "uv": [42, 69]}
					]
				},
				{
					"name": "left_toe3",
					"parent": "left_foot",
					"pivot": [3.73546, 1.02427, -3.26033],
					"cubes": [
						{"origin": [2.73546, 0.02427, -4.06033], "size": [1, 2, 1], "pivot": [3.73546, 1.02427, -4.76033], "rotation": [0, 7.5, 0], "uv": [49, 71]},
						{"origin": [3.23546, 0.02427, -7.06033], "size": [0, 2, 3], "pivot": [3.73546, 1.02427, -4.76033], "rotation": [0, 7.5, 0], "uv": [42, 72]}
					]
				},
				{
					"name": "right_toe3",
					"parent": "left_foot",
					"pivot": [6.01454, 1.02427, -2.76033],
					"rotation": [0, -32.5, 0],
					"cubes": [
						{"origin": [6.01454, 0.02427, -3.56033], "size": [1, 2, 1], "pivot": [6.01454, 1.02427, -4.26033], "rotation": [0, -7.5, 0], "uv": [49, 71], "mirror": true},
						{"origin": [6.51454, 0.02427, -6.56033], "size": [0, 2, 3], "pivot": [6.01454, 1.02427, -4.26033], "rotation": [0, -7.5, 0], "uv": [42, 72], "mirror": true}
					]
				},
				{
					"name": "left_toe2",
					"parent": "left_foot",
					"pivot": [4.9499, 1.52427, -2.93567],
					"cubes": [
						{"origin": [3, 0.02427, -3.97947], "size": [2, 2, 1], "pivot": [4.4, 6.42427, 1.02053], "rotation": [0, -12.5, 0], "uv": [42, 78]},
						{"origin": [4, 0.02427, -6.97947], "size": [0, 2, 3], "pivot": [4.4, 6.42427, 1.02053], "rotation": [0, -12.5, 0], "uv": [42, 72]}
					]
				},
				{
					"name": "right_leg",
					"parent": "lowerbody",
					"pivot": [-4.4, 9.42427, 1.02053],
					"cubes": [
						{"origin": [-7.40831, 5.8, -8.96571], "size": [5, 6, 6], "pivot": [-1.40831, 17.9, -3.96571], "rotation": [32.5, 12.5, 0], "uv": [87, 4], "mirror": true}
					]
				},
				{
					"name": "right_leg2",
					"parent": "right_leg",
					"pivot": [-4.4, 7.42427, 2.02053],
					"cubes": [
						{"origin": [-5.4, 1.82427, 0.02053], "size": [3, 7, 3], "pivot": [-4.4, 6.42427, 1.02053], "rotation": [-15, 12.5, 0], "uv": [19, 40], "mirror": true}
					]
				},
				{
					"name": "right_foot",
					"parent": "right_leg2",
					"pivot": [-4.4, 3.02427, 1.02053],
					"cubes": [
						{"origin": [-6, 0.02427, -2.97947], "size": [4, 3, 6], "pivot": [-4.4, 6.42427, 1.02053], "rotation": [0, 12.5, 0], "uv": [39, 26], "mirror": true}
					]
				},
				{
					"name": "left_toe4",
					"parent": "right_foot",
					"pivot": [-4.85, 1.27427, 2.27053],
					"cubes": [
						{"origin": [-5.8, 0.02427, 2.02053], "size": [2, 2, 2], "uv": [75, 51], "mirror": true},
						{"origin": [-4.9, 0.02427, 4.02053], "size": [0, 2, 3], "uv": [42, 69], "mirror": true}
					]
				},
				{
					"name": "left_toe5",
					"parent": "right_foot",
					"pivot": [-3.73546, 1.02427, -3.26033],
					"cubes": [
						{"origin": [-3.73546, 0.02427, -4.06033], "size": [1, 2, 1], "pivot": [-3.73546, 1.02427, -4.76033], "rotation": [0, -7.5, 0], "uv": [49, 71], "mirror": true},
						{"origin": [-3.23546, 0.02427, -7.06033], "size": [0, 2, 3], "pivot": [-3.73546, 1.02427, -4.76033], "rotation": [0, -7.5, 0], "uv": [42, 72], "mirror": true}
					]
				},
				{
					"name": "right_toe2",
					"parent": "right_foot",
					"pivot": [-6.01454, 1.02427, -2.76033],
					"rotation": [0, 32.5, 0],
					"cubes": [
						{"origin": [-7.01454, 0.02427, -3.56033], "size": [1, 2, 1], "pivot": [-6.01454, 1.02427, -4.26033], "rotation": [0, 7.5, 0], "uv": [49, 71]},
						{"origin": [-6.51454, 0.02427, -6.56033], "size": [0, 2, 3], "pivot": [-6.01454, 1.02427, -4.26033], "rotation": [0, 7.5, 0], "uv": [42, 72]}
					]
				},
				{
					"name": "left_toe6",
					"parent": "right_foot",
					"pivot": [-4.9499, 1.52427, -2.93567],
					"cubes": [
						{"origin": [-5, 0.02427, -3.97947], "size": [2, 2, 1], "pivot": [-4.4, 6.42427, 1.02053], "rotation": [0, 12.5, 0], "uv": [42, 78], "mirror": true},
						{"origin": [-4, 0.02427, -6.97947], "size": [0, 2, 3], "pivot": [-4.4, 6.42427, 1.02053], "rotation": [0, 12.5, 0], "uv": [42, 72], "mirror": true}
					]
				},
				{
					"name": "cloud",
					"parent": "lowerbody",
					"pivot": [0, 10.82197, 4.88519],
					"cubes": [
						{"origin": [-4.5, 8.66253, 7.69788], "size": [9, 9, 10], "inflate": 0.3, "pivot": [0, 8.36253, 12.44788], "rotation": [72.5, 0, 0], "uv": [54, 58]}
					]
				},
				{
					"name": "cloud2",
					"parent": "cloud",
					"pivot": [-0.5, 8.36253, 12.44788],
					"cubes": [
						{"origin": [-3.5, 3.66253, 8.69788], "size": [7, 5, 7], "pivot": [0, 8.36253, 12.44788], "rotation": [72.5, 0, 0], "uv": [94, 61]}
					]
				},
				{
					"name": "cloud3",
					"parent": "cloud2",
					"pivot": [0, 6.95902, 17.23947],
					"cubes": [
						{"origin": [-1.5, -1.33747, 10.69788], "size": [3, 5, 3], "pivot": [-0.5, 8.36253, 12.44788], "rotation": [72.5, 0, 0], "uv": [76, 78]}
					]
				},
				{
					"name": "tail",
					"parent": "lowerbody",
					"pivot": [0, 10.16935, 4.87182],
					"cubes": [
						{"origin": [-2, -0.54366, -1.1612], "size": [4, 5, 5], "inflate": 0.3, "pivot": [1, 8.65634, 0.0388], "rotation": [90, 0, 0], "uv": [0, 40]}
					]
				},
				{
					"name": "tail2",
					"parent": "tail",
					"pivot": [0, 10.41524, 9.60882],
					"cubes": [
						{"origin": [-2, -8.54366, -0.4612], "size": [4, 9, 4], "pivot": [1, 8.65634, 0.0388], "rotation": [90, 0, 0], "uv": [69, 36]},
						{"origin": [-2, -7.44366, 3.5388], "size": [4, 4, 4], "pivot": [1, 8.65634, 0.0388], "rotation": [90, 0, 0], "uv": [84, 47]}
					]
				},
				{
					"name": "tail3",
					"parent": "tail2",
					"pivot": [0, 10.48922, 17.33596],
					"cubes": [
						{"origin": [-2, -17.54366, -0.4612], "size": [4, 9, 4], "pivot": [1, 8.65634, 0.0388], "rotation": [90, 0, 0], "uv": [52, 36]},
						{"origin": [-2, -14.14366, 3.5388], "size": [4, 4, 4], "pivot": [1, 8.65634, 0.0388], "rotation": [90, 0, 0], "uv": [84, 47]}
					]
				},
				{
					"name": "tail4",
					"parent": "tail3",
					"pivot": [0, 10.37237, 26.00483],
					"cubes": [
						{"origin": [-2, -27.54366, -0.4612], "size": [4, 10, 4], "inflate": 0.3, "pivot": [1, 8.65634, 0.0388], "rotation": [90, 0, 0], "uv": [35, 36]},
						{"origin": [-2, -24.14366, 3.5388], "size": [4, 4, 4], "pivot": [1, 8.65634, 0.0388], "rotation": [90, 0, 0], "uv": [84, 47]}
					]
				},
				{
					"name": "tail5",
					"parent": "tail4",
					"pivot": [0, 9.93305, 36.48218],
					"cubes": [
						{"origin": [-2, -38.14366, -0.4612], "size": [4, 10, 4], "inflate": 0.5, "pivot": [1, 8.65634, 0.0388], "rotation": [90, 0, 0], "uv": [70, 2]},
						{"origin": [-3, 9.98647, 44.66893], "size": [6, 9, 9], "inflate": 0.5, "pivot": [1, 14.48647, 49.16893], "rotation": [120, 0, 0], "uv": [60, 17]},
						{"origin": [-2, -32.74366, 3.5388], "size": [4, 4, 4], "pivot": [1, 8.65634, 0.0388], "rotation": [90, 0, 0], "uv": [84, 47]}
					]
				},
				{
					"name": "body",
					"parent": "tornadustherian",
					"pivot": [0, 14.39611, -1.6781],
					"cubes": [
						{"origin": [-5.5, 12.4, -8.7], "size": [11, 10, 10], "pivot": [3.5, 17.9, -3.6], "rotation": [2.5, 0, 0], "uv": [0, 0]}
					]
				},
				{
					"name": "neck",
					"parent": "body",
					"pivot": [-0.5, 23.36764, -4.48295],
					"cubes": [
						{"origin": [-2.5, 21.76764, -7.48295], "size": [5, 4, 5], "pivot": [-0.5, 24.36764, -4.48295], "rotation": [10, 0, 0], "uv": [43, 15]}
					]
				},
				{
					"name": "head",
					"parent": "neck",
					"pivot": [0, 25.09683, -5.60453],
					"cubes": [
						{"origin": [-3, 24.76764, -8.48295], "size": [6, 5, 6], "pivot": [1, 24.36764, -4.48295], "rotation": [10, 0, 0], "uv": [91, 17]},
						{"origin": [-2, 25.76764, -2.48295], "size": [4, 4, 4], "pivot": [1, 24.36764, -4.48295], "rotation": [10, 0, 0], "uv": [89, 75]},
						{"origin": [-1.5, 24.71058, -1.53413], "size": [3, 3, 3], "pivot": [0.5, 28.41058, -1.13413], "rotation": [-32.5, 0, 0], "uv": [106, 76]},
						{"origin": [-1, 22.85561, -3.73171], "size": [2, 2, 2], "pivot": [0, 23.85561, -2.73171], "rotation": [-40, 0, 0], "uv": [58, 79]},
						{"origin": [-2, 29.48157, -9.65276], "size": [4, 4, 4], "pivot": [-1, 31.48157, -6.75276], "rotation": [30, 0, 0], "uv": [83, 59]},
						{"origin": [0, 22.41058, -7.13413], "size": [0, 6, 7], "pivot": [1, 28.41058, -1.13413], "rotation": [-110, 0, 0], "uv": [0, 73]},
						{"origin": [-1.05912, 24.61223, -10.3158], "size": [2, 2, 2], "pivot": [0.14088, 25.61223, -8.5158], "rotation": [7.40702, -6.73717, 42.06341], "uv": [67, 79]},
						{"origin": [-6.5026, 19.98512, -8.8604], "size": [6, 5, 0], "pivot": [-3.0026, 25.98512, -9.0604], "rotation": [70.74622, -9.84655, 100.15108], "uv": [101, 43]},
						{"origin": [0.5026, 19.98512, -8.8604], "size": [6, 5, 0], "pivot": [3.0026, 25.98512, -9.0604], "rotation": [70.74622, 9.84655, -100.15108], "uv": [101, 43], "mirror": true},
						{"origin": [2.17523, 24.69227, -8.98744], "size": [1, 2, 1], "inflate": 0.2, "pivot": [2.67523, 25.99227, -8.68744], "rotation": [43.24622, 9.84655, -100.15108], "uv": [116, 64], "mirror": true},
						{"origin": [1.78283, 26.10676, -9.97236], "size": [1, 1, 1], "pivot": [2.48283, 25.90676, -8.87236], "rotation": [-7.96341, 6.06809, -142.92277], "uv": [106, 58], "mirror": true},
						{"origin": [0.50562, 24.65025, -9.32713], "size": [1, 2, 1], "inflate": 0.3, "pivot": [1.00562, 25.65025, -8.82713], "rotation": [-1.75378, 9.84655, -100.15108], "uv": [101, 57], "mirror": true},
						{"origin": [-0.38443, 26.10764, -9.47117], "size": [4, 3, 0], "pivot": [1.61557, 27.60764, -9.47117], "rotation": [-2.85521, -7.4118, -14.28606], "uv": [88, 43], "mirror": true},
						{"origin": [-0.94088, 24.61223, -10.3158], "size": [2, 2, 2], "pivot": [-0.14088, 25.61223, -8.5158], "rotation": [7.40702, 6.73717, -42.06341], "uv": [67, 79], "mirror": true},
						{"origin": [-2.78283, 26.10676, -9.97236], "size": [1, 1, 1], "pivot": [-2.48283, 25.90676, -8.87236], "rotation": [-7.96341, -6.06809, 142.92277], "uv": [106, 58]},
						{"origin": [-1.50562, 24.65025, -9.32713], "size": [1, 2, 1], "inflate": 0.3, "pivot": [-1.00562, 25.65025, -8.82713], "rotation": [-1.75378, -9.84655, 100.15108], "uv": [101, 57]},
						{"origin": [-3.61557, 26.10764, -9.47117], "size": [4, 3, 0], "pivot": [-1.61557, 27.60764, -9.47117], "rotation": [-2.85521, 7.4118, 14.28606], "uv": [88, 43]},
						{"origin": [-3.17523, 24.69227, -8.98744], "size": [1, 2, 1], "inflate": 0.2, "pivot": [-2.67523, 25.99227, -8.68744], "rotation": [43.24622, -9.84655, 100.15108], "uv": [116, 64]}
					]
				},
				{
					"name": "right_antenna",
					"parent": "head",
					"pivot": [-1.86189, 29.68111, -7.01841],
					"cubes": [
						{"origin": [-3.6, 28.23112, -8.24034], "size": [2, 3, 2], "pivot": [-3, 29.73112, -7.24034], "rotation": [-18.19144, -13.47157, -35.3335], "uv": [33, 77]}
					]
				},
				{
					"name": "right_antenna2",
					"parent": "right_antenna",
					"pivot": [-3, 29.73112, -7.24034]
				},
				{
					"name": "right_antenna3",
					"parent": "right_antenna2",
					"pivot": [-3.45151, 31.04362, -6.70404],
					"cubes": [
						{"origin": [-2.5, 31.23112, -8.24034], "size": [0, 4, 2], "pivot": [-3, 29.73112, -7.24034], "rotation": [-18.19144, -13.47157, -35.3335], "uv": [28, 75]}
					]
				},
				{
					"name": "right_antenna4",
					"parent": "right_antenna3",
					"pivot": [-5.91903, 34.25955, -5.34683],
					"cubes": [
						{"origin": [-2.5, 35.23112, -8.24034], "size": [0, 4, 2], "pivot": [-3, 29.73112, -7.24034], "rotation": [-18.19144, -13.47157, -35.3335], "uv": [53, 77]}
					]
				},
				{
					"name": "left_antenna",
					"parent": "head",
					"pivot": [1.86189, 29.68111, -7.01841],
					"cubes": [
						{"origin": [1.6, 28.23112, -8.24034], "size": [2, 3, 2], "pivot": [3, 29.73112, -7.24034], "rotation": [-18.19144, 13.47157, 35.3335], "uv": [33, 77], "mirror": true}
					]
				},
				{
					"name": "left_antenna2",
					"parent": "left_antenna",
					"pivot": [3, 29.73112, -7.24034]
				},
				{
					"name": "left_antenna3",
					"parent": "left_antenna2",
					"pivot": [3.45151, 31.04362, -6.70404],
					"cubes": [
						{"origin": [2.5, 31.23112, -8.24034], "size": [0, 4, 2], "pivot": [3, 29.73112, -7.24034], "rotation": [-18.19144, 13.47157, 35.3335], "uv": [28, 75], "mirror": true}
					]
				},
				{
					"name": "left_antenna4",
					"parent": "left_antenna3",
					"pivot": [5.91903, 34.25955, -5.34683],
					"cubes": [
						{"origin": [2.5, 35.23112, -8.24034], "size": [0, 4, 2], "pivot": [3, 29.73112, -7.24034], "rotation": [-18.19144, 13.47157, 35.3335], "uv": [53, 77], "mirror": true}
					]
				},
				{
					"name": "left_wing",
					"parent": "body",
					"pivot": [5.04731, 22.4002, -3.83661],
					"cubes": [
						{"origin": [5, 20.33697, -4.82873], "size": [10, 2, 2], "pivot": [10, 21.33697, -3.82873], "rotation": [20, 0, 0], "uv": [25, 51]},
						{"origin": [5, 11.4, -1.2], "size": [13, 10, 0], "pivot": [20.75, 17.25, 0], "rotation": [20, 0, 0], "uv": [0, 57]}
					]
				},
				{
					"name": "left_wing2",
					"parent": "left_wing",
					"pivot": [14.56308, 22.22063, -3.83788],
					"cubes": [
						{"origin": [16.21514, 14.04888, -3.16411], "size": [13, 10, 0], "pivot": [21.96514, 19.89888, -0.96411], "rotation": [18.25612, 8.31087, -23.66235], "uv": [0, 68]},
						{"origin": [16.21514, 24.04888, -4.16411], "size": [10, 2, 2], "pivot": [21.96514, 19.89888, -0.96411], "rotation": [18.25612, 8.31087, -23.66235], "uv": [0, 51]}
					]
				},
				{
					"name": "bone3",
					"parent": "left_wing2",
					"pivot": [23.44136, 25.2172, -6.15787],
					"cubes": [
						{"origin": [27.46769, 10.74597, -2.05386], "size": [13, 13, 0], "pivot": [23.21769, 19.59597, -0.85386], "rotation": [16.10644, 12.0174, -35.79355], "uv": [27, 57]},
						{"origin": [27.46769, 23.74597, -4.05386], "size": [10, 2, 2], "pivot": [23.21769, 19.59597, -0.85386], "rotation": [16.10644, 12.0174, -35.79355], "uv": [50, 51]},
						{"origin": [32.46769, 27.74597, -3.05386], "size": [3, 4, 0], "pivot": [23.21769, 19.59597, -0.85386], "rotation": [16.10644, 12.0174, -35.79355], "uv": [49, 79]},
						{"origin": [30.46769, 25.74597, -4.05386], "size": [5, 2, 2], "pivot": [23.21769, 19.59597, -0.85386], "rotation": [16.10644, 12.0174, -35.79355], "uv": [27, 72]}
					]
				},
				{
					"name": "left_wing3",
					"parent": "body",
					"pivot": [-5.04731, 22.4002, -3.83661],
					"cubes": [
						{"origin": [-15, 20.33697, -4.82873], "size": [10, 2, 2], "pivot": [-10, 21.33697, -3.82873], "rotation": [20, 0, 0], "uv": [25, 51], "mirror": true},
						{"origin": [-18, 11.4, -1.2], "size": [13, 10, 0], "pivot": [-20.75, 17.25, 0], "rotation": [20, 0, 0], "uv": [0, 57], "mirror": true}
					]
				},
				{
					"name": "right_wing2",
					"parent": "left_wing3",
					"pivot": [-14.56308, 22.22063, -3.83788],
					"cubes": [
						{"origin": [-29.21514, 14.04888, -3.16411], "size": [13, 10, 0], "pivot": [-21.96514, 19.89888, -0.96411], "rotation": [18.25612, -8.31087, 23.66235], "uv": [0, 68], "mirror": true},
						{"origin": [-26.21514, 24.04888, -4.16411], "size": [10, 2, 2], "pivot": [-21.96514, 19.89888, -0.96411], "rotation": [18.25612, -8.31087, 23.66235], "uv": [0, 51], "mirror": true}
					]
				},
				{
					"name": "bone4",
					"parent": "right_wing2",
					"pivot": [-23.44136, 25.2172, -6.15787],
					"cubes": [
						{"origin": [-40.46769, 10.74597, -2.05386], "size": [13, 13, 0], "pivot": [-23.21769, 19.59597, -0.85386], "rotation": [16.10644, -12.0174, 35.79355], "uv": [27, 57], "mirror": true},
						{"origin": [-37.46769, 23.74597, -4.05386], "size": [10, 2, 2], "pivot": [-23.21769, 19.59597, -0.85386], "rotation": [16.10644, -12.0174, 35.79355], "uv": [50, 51], "mirror": true},
						{"origin": [-35.46769, 27.74597, -3.05386], "size": [3, 4, 0], "pivot": [-23.21769, 19.59597, -0.85386], "rotation": [16.10644, -12.0174, 35.79355], "uv": [49, 79], "mirror": true},
						{"origin": [-35.46769, 25.74597, -4.05386], "size": [5, 2, 2], "pivot": [-23.21769, 19.59597, -0.85386], "rotation": [16.10644, -12.0174, 35.79355], "uv": [27, 72], "mirror": true}
					]
				},
				{
					"name": "lowerbody",
					"parent": "tornadustherian",
					"pivot": [0, 15.43809, -2.28474]
				},
				{
					"name": "right_leg",
					"parent": "lowerbody",
					"pivot": [-4.4, 9.42427, 1.02053]
				},
				{
					"name": "right_leg2",
					"parent": "right_leg",
					"pivot": [-4.4, 7.42427, 2.02053]
				},
				{
					"name": "right_foot",
					"parent": "right_leg2",
					"pivot": [-4.4, 3.02427, 1.02053]
				},
				{
					"name": "right_toe",
					"parent": "right_foot",
					"pivot": [-4.4, 6.42427, 1.02053]
				}
			]
		}
	]
}